scenarioxp/__init__.py
scenarioxp/scenarioxp.py
scenarioxp-0.1.1.dist-info/LICENSE
scenarioxp-0.1.1.dist-info/METADATA
scenarioxp-0.1.1.dist-info/WHEEL
scenarioxp-0.1.1.dist-info/top_level.txt
scenarioxp-0.1.1.dist-info/RECORD
