Metadata-Version: 2.1
Name: scenarioxp
Version: 0.1.1
Summary: A toolkit for targeted scenario selection.
Home-page: https://github.com/AkbasLab/scenarioxp
Author: Quentin Goss
Author-email: gossq@my.erau.edu
License: LICENSE
Project-URL: Bug Tracker, https://github.com/AkbasLab/scenarioxp/issues
Platform: UNKNOWN
Classifier: Programming Language :: Python :: 3
Classifier: License :: OSI Approved :: MIT License
Classifier: Operating System :: OS Independent
Requires-Python: >= 3.9
License-File: LICENSE
Requires-Dist: numpy >=1.21.1
Requires-Dist: scipy >=1.7.1
Requires-Dist: pandas >=1.3.2
Requires-Dist: sim-bug-tools >=1.0.1
